x0m3l50ajg9f/__init__.py
x0m3l50ajg9f/example.py
x0m3l50ajg9f-0.0.1.dist-info/METADATA
x0m3l50ajg9f-0.0.1.dist-info/WHEEL
x0m3l50ajg9f-0.0.1.dist-info/RECORD
